{
    "1": {
        "nome": "Primeiro",
        "idade": 1,
        "sexo": "F",
        "rg": 1222222222,
        "cpf": 12222222224,
        "id": 1
    },
    "2": {
        "nome": "Segundo",
        "idade": 2,
        "sexo": "M",
        "rg": 2222222225,
        "cpf": 22222222255,
        "id": 1
    },
    "3": {
        "nome": "Terceiro",
        "idade": 3,
        "sexo": "F",
        "rg": 2323232323,
        "cpf": 23232323235,
        "id": 1
    },
    "4": {
        "nome": "Quarto",
        "idade": 4,
        "sexo": "F",
        "rg": 2525852588,
        "cpf": 25258525889,
        "id": 3
    }
}